clustice/__init__.py
clustice/geometry.py
clustice/graph.py
clustice/gromacs.py
clustice/serialize.py
clustice/solid.py
clustice/water.py
clustice/yaplot.py
clustice-0.7.3.dist-info/LICENSE
clustice-0.7.3.dist-info/METADATA
clustice-0.7.3.dist-info/WHEEL
clustice-0.7.3.dist-info/RECORD
