Metadata-Version: 2.1
Name: ClustIce
Version: 0.7.3
Summary: A tool to generate exotic ice clusters.
Home-page: https://github.com/vitroid/ClustIce
License: MIT
Author: Masakazu Matsumoto
Author-email: vitroid@gmail.com
Requires-Python: >=3.10,<4.0
Classifier: License :: OSI Approved :: MIT License
Classifier: Programming Language :: Python :: 3
Classifier: Programming Language :: Python :: 3.10
Classifier: Programming Language :: Python :: 3.11
Classifier: Programming Language :: Python :: 3.12
Requires-Dist: cycless (>=0.4.2)
Requires-Dist: icecream (>=2.1.3,<3.0.0)
Requires-Dist: networkx (>=3.2.1)
Requires-Dist: numpy (>=1.26.4)
Requires-Dist: pairlist (>=0.5.1.3,<0.6.0.0)
Requires-Dist: scikit-learn (>=1.3.2,<2.0.0)
Requires-Dist: yaplotlib (>=0.1.2,<0.2.0)
Project-URL: Repository, https://github.com/vitroid/ClustIce
